multimeter/__init__.py
multimeter/utils/n_particles.py
multimeter/utils/utils.py
multimeter_tension-0.1.1.dist-info/licenses/LICENSE
multimeter_tension-0.1.1.dist-info/METADATA
multimeter_tension-0.1.1.dist-info/WHEEL
multimeter_tension-0.1.1.dist-info/top_level.txt
multimeter_tension-0.1.1.dist-info/RECORD
