Metadata-Version: 2.4
Name: multimeter-tension
Version: 0.1.1
Summary: Generalized tension metrics for multiple cosmological datasets
Author: Matías Leizerovich
License: MIT License
Project-URL: Homepage, https://github.com/matiasleize/multimeter
Project-URL: Repository, https://github.com/matiasleize/multimeter
Project-URL: Issues, https://github.com/matiasleize/multimeter/issues
Project-URL: Documentation, https://multimeter-tension.readthedocs.io/
Keywords: cosmology,statistics,tension,bayesian,inference
Requires-Python: >=3.10
License-File: LICENSE
Requires-Dist: numpy>=1.23
Requires-Dist: scipy>=1.10
Requires-Dist: matplotlib>=3.7
Provides-Extra: notebooks
Requires-Dist: jupyter; extra == "notebooks"
Requires-Dist: ipykernel; extra == "notebooks"
Provides-Extra: docs
Requires-Dist: sphinx>=7; extra == "docs"
Requires-Dist: sphinx-rtd-theme>=2; extra == "docs"
Requires-Dist: myst-parser>=2; extra == "docs"
Provides-Extra: dev
Requires-Dist: build; extra == "dev"
Requires-Dist: twine; extra == "dev"
Requires-Dist: pytest>=7; extra == "dev"
Requires-Dist: ruff; extra == "dev"
Requires-Dist: black; extra == "dev"
Dynamic: license-file
